.coveragerc
.hgignore
.hgtags
CHANGES.rst
HACKING.rst
LICENSE.txt
MANIFEST.in
README.rst
bootstrap.py
buildout.cfg
pytest.ini
setup.py
tox.ini
src/gocept/__init__.py
src/gocept.package.egg-info/PKG-INFO
src/gocept.package.egg-info/SOURCES.txt
src/gocept.package.egg-info/dependency_links.txt
src/gocept.package.egg-info/entry_points.txt
src/gocept.package.egg-info/namespace_packages.txt
src/gocept.package.egg-info/not-zip-safe
src/gocept.package.egg-info/requires.txt
src/gocept.package.egg-info/top_level.txt
src/gocept/package/__init__.py
src/gocept/package/doc.py
src/gocept/package/skeleton.py
src/gocept/package/sphinxconf.py
src/gocept/package/skeleton/CHANGES.rst_tmpl
src/gocept/package/skeleton/HACKING.rst_tmpl
src/gocept/package/skeleton/LICENSE.txt_tmpl
src/gocept/package/skeleton/README.rst_tmpl
src/gocept/package/skeleton/bootstrap.py
src/gocept/package/skeleton/buildout.cfg_tmpl
src/gocept/package/skeleton/coveragerc_tmpl
src/gocept/package/skeleton/hgignore_tmpl
src/gocept/package/skeleton/hgrc_tmpl
src/gocept/package/skeleton/local.cfg_tmpl
src/gocept/package/skeleton/pytest.ini
src/gocept/package/skeleton/setup.py_tmpl
src/gocept/package/skeleton/doc/about.txt_tmpl
src/gocept/package/skeleton/doc/api.txt_tmpl
src/gocept/package/skeleton/doc/changes.txt_tmpl
src/gocept/package/skeleton/doc/conf.py_tmpl
src/gocept/package/skeleton/doc/index.txt_tmpl
src/gocept/package/skeleton/src/+namespace+/__init__.py
src/gocept/package/skeleton/src/+namespace+/+package+/__init__.py
src/gocept/package/skeleton/src/+namespace+/+package+/tests/__init__.py
src/gocept/package/skeleton/src/+namespace+/+package+/tests/test_example.py
src/gocept/package/skeleton/versions/versions.cfg_tmpl
src/gocept/package/skeleton/versions/ztk-versions-1.1.5.cfg
src/gocept/package/tests/__init__.py
src/gocept/package/tests/test_doc.py
src/gocept/package/tests/test_skeleton.py
src/gocept/package/themes/gocept/project-links.html
src/gocept/package/themes/gocept/theme.conf
src/gocept/package/themes/gocept/static/favicon.ico
src/gocept/package/themes/gocept/static/gocept.css
src/gocept/package/themes/gocept/static/gocept.png
src/gocept/package/themes/gocept/templates/autosummary/module.rst
src/gocept/package/webapp-deployment-skeleton/HACKING.txt_tmpl
src/gocept/package/webapp-deployment-skeleton/README.txt_tmpl
