Metadata-Version: 2.1
Name: gocept.package
Version: 3.1
Summary: A paste.script template following gocept Python package conventions.
Home-page: https://bitbucket.org/gocept/gocept.package/
Author: gocept <mail@gocept.com>
Author-email: mail@gocept.com
License: ZPL 2.1
Keywords: paste.script paster create template python package sphinx themedeployment batou webapp
Platform: UNKNOWN
Classifier: Environment :: Plugins
Classifier: Framework :: Paste
Classifier: Intended Audience :: Developers
Classifier: License :: OSI Approved :: MIT License
Classifier: Programming Language :: Python
Classifier: Programming Language :: Python :: 2
Classifier: Programming Language :: Python :: 2.7
Classifier: Programming Language :: Python :: 3
Classifier: Programming Language :: Python :: 3.4
Classifier: Programming Language :: Python :: 3.5
Classifier: Programming Language :: Python :: Implementation :: CPython
Classifier: Programming Language :: Python :: Implementation :: PyPy
Provides-Extra: test
Provides-Extra: doc
